sarapy/__init__.py
sarapy/version.py
sarapy/analysis/FeaturesResume.py
sarapy/analysis/__init__.py
sarapy/dataProcessing/GeoProcessor.py
sarapy/dataProcessing/OpsProcessor.py
sarapy/dataProcessing/TLMSensorDataProcessor.py
sarapy/dataProcessing/TimeSeriesProcessor.py
sarapy/dataProcessing/__init__.py
sarapy/mlProcessors/FertilizerFMCreator.py
sarapy/mlProcessors/FertilizerTransformer.py
sarapy/mlProcessors/PlantinClassifier.py
sarapy/mlProcessors/PlantinFMCreator.py
sarapy/mlProcessors/__init__.py
sarapy/preprocessing/DistancesImputer.py
sarapy/preprocessing/FertilizerImputer.py
sarapy/preprocessing/TransformInputData.py
sarapy/preprocessing/TransformToOutputData.py
sarapy/preprocessing/__init__.py
sarapy/stats/__init__.py
sarapy/stats/stats.py
sarapy/utils/__init__.py
sarapy/utils/plotting.py
sarapy/utils/utils.py
sarapy-3.0.0.dist-info/LICENCE
sarapy-3.0.0.dist-info/METADATA
sarapy-3.0.0.dist-info/WHEEL
sarapy-3.0.0.dist-info/top_level.txt
sarapy-3.0.0.dist-info/RECORD
