Metadata-Version: 2.1
Name: sarapy
Version: 3.0.0
Home-page: https://github.com/lucasbaldezzari/sarapy
Author: Lucas Baldezzari
Author-email: Lucas Baldezzari <lmbaldezzari@gmail.com>
Maintainer-email: Lucas Baldezzari <lmbaldezzari@gmail.com>
License: For private use only. Owner AMG Servicios profesionales (Mercedes, Uruguay)
License-File: LICENCE
Requires-Dist: numpy
Requires-Dist: matplotlib
Requires-Dist: pandas
Requires-Dist: scipy
Requires-Dist: scikit-learn
Requires-Dist: geopy
